BitParser/BitParser.py
BitParser/__init__.py
bit_parser-1.3.2.dist-info/LICENSE
bit_parser-1.3.2.dist-info/METADATA
bit_parser-1.3.2.dist-info/WHEEL
bit_parser-1.3.2.dist-info/top_level.txt
bit_parser-1.3.2.dist-info/RECORD
