Metadata-Version: 2.1
Name: bit-parser
Version: 1.3.2
Summary: Parse compact bitfields (bitmaps, flag sets) represented as hex strings.
Author-email: Vitalij Gotovskij <vitalij@cdeveloper.eu>
License: MIT License
Project-URL: Homepage, https://github.com/vitalij555/bit-parser
Project-URL: Issues, https://github.com/vitalij555/bit-parser/issues
Project-URL: Repository, https://github.com/vitalij555/bit-parser
Keywords: bit,bitfield,bitmap,protocol,parser
Classifier: Development Status :: 5 - Production/Stable
Classifier: Intended Audience :: Developers
Classifier: Topic :: Software Development :: Libraries
Classifier: Topic :: Software Development :: Libraries :: Python Modules
Classifier: Operating System :: OS Independent
Classifier: License :: OSI Approved :: MIT License
Classifier: Programming Language :: Python :: 3.8
Classifier: Programming Language :: Python :: 3.9
Classifier: Programming Language :: Python :: 3.10
Classifier: Programming Language :: Python :: 3.11
Classifier: Programming Language :: Python :: 3.12
Requires-Python: >=3.8
License-File: LICENSE
Requires-Dist: bitops
